<?xml version="1.0" encoding="utf-8"?>
<odoo>
    <template id="conatct_us_form_inherit" name="conatct us form inherit" inherit_id="website.contactus">
        <xpath expr="//div[@class='mb-0 py-2 col-12 s_website_form_submit']" position="before">
            <div class="mb-0 py-2 col-12 s_website_form_field s_website_form_custom s_website_form_required"
                 data-type="binary" data-name="Field">
                <div class="row s_col_no_resize s_col_no_bgcolor">
                    <label class="col-form-label col-sm-auto s_website_form_label" style="width: 200px"
                           for="file_input">
                        <span class="s_website_form_label_content">Attachment</span>
                        <span class="s_website_form_mark">*</span>
                    </label>
                    <div class="col-sm">
                        <input type="file" id="attachments" class="form-control s_website_form_input get_attach" name="attachments"
                               required=""/>
                    </div>
                </div>
            </div>
        </xpath>
    </template>

<!--    <template id="contactus_form_inherit" name="Contact Form (Opportunity)" inherit_id="website.contactus">-->
<!--            <xpath expr="//t[@t-set='contactus_form_values']" position="after">-->
<!--            <t t-set="contactus_form_values" t-value="dict(contactus_form_values, **{-->
<!--                    'contact_name': request.params.get('contact_name', ''),-->
<!--                    'partner_name': request.params.get('partner_name', ''),-->
<!--                    'description': request.params.get('description', ''),-->
<!--                    'attachments': request.params.get('attachment', ''),-->
<!--                })"/>-->
<!--        </xpath>-->
<!--    </template>-->

</odoo>
